[
  {
    "inputs": [
      {
        "internalType": "address",
        "name": "_gmdToken",
        "type": "address"
      },
      {
        "internalType": "address",
        "name": "_lpToken",
        "type": "address"
      },
      {
        "internalType": "address",
        "name": "_oracle",
        "type": "address"
      },
      {
        "internalType": "address",
        "name": "_treasury",
        "type": "address"
      },
      {
        "internalType": "address",
        "name": "_inviteReward",
        "type": "address"
      },
      {
        "internalType": "address",
        "name": "_stakingReward",
        "type": "address"
      },
      {
        "internalType": "address",
        "name": "_payee",
        "type": "address"
      },
      {
        "internalType": "address",
        "name": "_builder",
        "type": "address"
      },
      {
        "internalType": "address",
        "name": "_tech",
        "type": "address"
      }
    ],
    "stateMutability": "nonpayable",
    "type": "constructor"
  },
  {
    "anonymous": false,
    "inputs": [
      {
        "indexed": true,
        "internalType": "address",
        "name": "pre",
        "type": "address"
      },
      {
        "indexed": true,
        "internalType": "address",
        "name": "newBuilder",
        "type": "address"
      }
    ],
    "name": "BuilderUpdated",
    "type": "event"
  },
  {
    "anonymous": false,
    "inputs": [
      {
        "indexed": false,
        "internalType": "bytes32",
        "name": "orderHash",
        "type": "bytes32"
      },
      {
        "indexed": true,
        "internalType": "address",
        "name": "token",
        "type": "address"
      },
      {
        "indexed": true,
        "internalType": "address",
        "name": "account",
        "type": "address"
      },
      {
        "indexed": false,
        "internalType": "uint256",
        "name": "amount",
        "type": "uint256"
      }
    ],
    "name": "Deposited",
    "type": "event"
  },
  {
    "anonymous": false,
    "inputs": [
      {
        "indexed": false,
        "internalType": "uint256",
        "name": "pre",
        "type": "uint256"
      },
      {
        "indexed": false,
        "internalType": "uint256",
        "name": "newAmount",
        "type": "uint256"
      }
    ],
    "name": "MinStakingUpdated",
    "type": "event"
  },
  {
    "anonymous": false,
    "inputs": [
      {
        "indexed": true,
        "internalType": "address",
        "name": "previousOwner",
        "type": "address"
      },
      {
        "indexed": true,
        "internalType": "address",
        "name": "newOwner",
        "type": "address"
      }
    ],
    "name": "OwnershipTransferred",
    "type": "event"
  },
  {
    "anonymous": false,
    "inputs": [
      {
        "indexed": false,
        "internalType": "address",
        "name": "account",
        "type": "address"
      }
    ],
    "name": "Paused",
    "type": "event"
  },
  {
    "anonymous": false,
    "inputs": [
      {
        "indexed": true,
        "internalType": "address",
        "name": "pre",
        "type": "address"
      },
      {
        "indexed": true,
        "internalType": "address",
        "name": "newPayee",
        "type": "address"
      }
    ],
    "name": "PayeeUpdated",
    "type": "event"
  },
  {
    "anonymous": false,
    "inputs": [
      {
        "indexed": false,
        "internalType": "uint24",
        "name": "pre",
        "type": "uint24"
      },
      {
        "indexed": false,
        "internalType": "uint24",
        "name": "newFee",
        "type": "uint24"
      }
    ],
    "name": "PoolFeeUpdated",
    "type": "event"
  },
  {
    "anonymous": false,
    "inputs": [
      {
        "indexed": true,
        "internalType": "address",
        "name": "pre",
        "type": "address"
      },
      {
        "indexed": true,
        "internalType": "address",
        "name": "newOracle",
        "type": "address"
      }
    ],
    "name": "PriceOracleUpdated",
    "type": "event"
  },
  {
    "anonymous": false,
    "inputs": [
      {
        "indexed": true,
        "internalType": "address",
        "name": "token",
        "type": "address"
      },
      {
        "indexed": false,
        "internalType": "uint256",
        "name": "preRate",
        "type": "uint256"
      },
      {
        "indexed": false,
        "internalType": "uint256",
        "name": "newRate",
        "type": "uint256"
      }
    ],
    "name": "SavingsRateUpdated",
    "type": "event"
  },
  {
    "anonymous": false,
    "inputs": [
      {
        "indexed": true,
        "internalType": "address",
        "name": "pre",
        "type": "address"
      },
      {
        "indexed": true,
        "internalType": "address",
        "name": "newTech",
        "type": "address"
      }
    ],
    "name": "TechUpdated",
    "type": "event"
  },
  {
    "anonymous": false,
    "inputs": [
      {
        "indexed": true,
        "internalType": "address",
        "name": "pre",
        "type": "address"
      },
      {
        "indexed": true,
        "internalType": "address",
        "name": "newTreasury",
        "type": "address"
      }
    ],
    "name": "TreasuryUpdated",
    "type": "event"
  },
  {
    "anonymous": false,
    "inputs": [
      {
        "indexed": false,
        "internalType": "address",
        "name": "account",
        "type": "address"
      }
    ],
    "name": "Unpaused",
    "type": "event"
  },
  {
    "anonymous": false,
    "inputs": [
      {
        "indexed": false,
        "internalType": "bytes32",
        "name": "orderHash",
        "type": "bytes32"
      },
      {
        "indexed": true,
        "internalType": "address",
        "name": "token",
        "type": "address"
      },
      {
        "indexed": false,
        "internalType": "uint256",
        "name": "_periodFinish",
        "type": "uint256"
      }
    ],
    "name": "UserPeriodFinishUpdated",
    "type": "event"
  },
  {
    "anonymous": false,
    "inputs": [
      {
        "indexed": false,
        "internalType": "bytes32",
        "name": "orderHash",
        "type": "bytes32"
      },
      {
        "indexed": true,
        "internalType": "address",
        "name": "token",
        "type": "address"
      },
      {
        "indexed": true,
        "internalType": "address",
        "name": "account",
        "type": "address"
      },
      {
        "indexed": false,
        "internalType": "uint256",
        "name": "amount",
        "type": "uint256"
      },
      {
        "indexed": false,
        "internalType": "uint256",
        "name": "interest",
        "type": "uint256"
      }
    ],
    "name": "Withdrawn",
    "type": "event"
  },
  {
    "inputs": [],
    "name": "BUILDER_FEE",
    "outputs": [
      {
        "internalType": "uint256",
        "name": "",
        "type": "uint256"
      }
    ],
    "stateMutability": "view",
    "type": "function"
  },
  {
    "inputs": [],
    "name": "CLAIM_PERCENTAGE",
    "outputs": [
      {
        "internalType": "uint256",
        "name": "",
        "type": "uint256"
      }
    ],
    "stateMutability": "view",
    "type": "function"
  },
  {
    "inputs": [],
    "name": "FEE",
    "outputs": [
      {
        "internalType": "uint256",
        "name": "",
        "type": "uint256"
      }
    ],
    "stateMutability": "view",
    "type": "function"
  },
  {
    "inputs": [],
    "name": "REWARD_DURATION",
    "outputs": [
      {
        "internalType": "uint256",
        "name": "",
        "type": "uint256"
      }
    ],
    "stateMutability": "view",
    "type": "function"
  },
  {
    "inputs": [],
    "name": "STAKING_PERCENTAGE",
    "outputs": [
      {
        "internalType": "uint256",
        "name": "",
        "type": "uint256"
      }
    ],
    "stateMutability": "view",
    "type": "function"
  },
  {
    "inputs": [],
    "name": "TECH_FEE",
    "outputs": [
      {
        "internalType": "uint256",
        "name": "",
        "type": "uint256"
      }
    ],
    "stateMutability": "view",
    "type": "function"
  },
  {
    "inputs": [],
    "name": "USDT",
    "outputs": [
      {
        "internalType": "address",
        "name": "",
        "type": "address"
      }
    ],
    "stateMutability": "view",
    "type": "function"
  },
  {
    "inputs": [],
    "name": "WETH",
    "outputs": [
      {
        "internalType": "address",
        "name": "",
        "type": "address"
      }
    ],
    "stateMutability": "view",
    "type": "function"
  },
  {
    "inputs": [],
    "name": "builder",
    "outputs": [
      {
        "internalType": "address",
        "name": "",
        "type": "address"
      }
    ],
    "stateMutability": "view",
    "type": "function"
  },
  {
    "inputs": [],
    "name": "checkUpkeep",
    "outputs": [
      {
        "internalType": "bool",
        "name": "upkeepNeeded",
        "type": "bool"
      },
      {
        "internalType": "bytes",
        "name": "performData",
        "type": "bytes"
      }
    ],
    "stateMutability": "view",
    "type": "function"
  },
  {
    "inputs": [
      {
        "internalType": "bytes32",
        "name": "orderHash",
        "type": "bytes32"
      }
    ],
    "name": "claim",
    "outputs": [],
    "stateMutability": "nonpayable",
    "type": "function"
  },
  {
    "inputs": [
      {
        "internalType": "address",
        "name": "token",
        "type": "address"
      },
      {
        "internalType": "address",
        "name": "inviter",
        "type": "address"
      },
      {
        "internalType": "uint256",
        "name": "amount",
        "type": "uint256"
      }
    ],
    "name": "deposit",
    "outputs": [],
    "stateMutability": "payable",
    "type": "function"
  },
  {
    "inputs": [
      {
        "internalType": "bytes32",
        "name": "orderHash",
        "type": "bytes32"
      }
    ],
    "name": "earned",
    "outputs": [
      {
        "internalType": "uint256",
        "name": "",
        "type": "uint256"
      }
    ],
    "stateMutability": "view",
    "type": "function"
  },
  {
    "inputs": [],
    "name": "gmdToken",
    "outputs": [
      {
        "internalType": "address",
        "name": "",
        "type": "address"
      }
    ],
    "stateMutability": "view",
    "type": "function"
  },
  {
    "inputs": [
      {
        "internalType": "address",
        "name": "",
        "type": "address"
      }
    ],
    "name": "interestPerStored",
    "outputs": [
      {
        "internalType": "uint256",
        "name": "",
        "type": "uint256"
      }
    ],
    "stateMutability": "view",
    "type": "function"
  },
  {
    "inputs": [
      {
        "internalType": "address",
        "name": "token",
        "type": "address"
      }
    ],
    "name": "interestPerToken",
    "outputs": [
      {
        "internalType": "uint256",
        "name": "",
        "type": "uint256"
      }
    ],
    "stateMutability": "view",
    "type": "function"
  },
  {
    "inputs": [],
    "name": "inviteReward",
    "outputs": [
      {
        "internalType": "address",
        "name": "",
        "type": "address"
      }
    ],
    "stateMutability": "view",
    "type": "function"
  },
  {
    "inputs": [
      {
        "internalType": "address",
        "name": "",
        "type": "address"
      }
    ],
    "name": "lastUpdateTime",
    "outputs": [
      {
        "internalType": "uint256",
        "name": "",
        "type": "uint256"
      }
    ],
    "stateMutability": "view",
    "type": "function"
  },
  {
    "inputs": [],
    "name": "lpToken",
    "outputs": [
      {
        "internalType": "address",
        "name": "",
        "type": "address"
      }
    ],
    "stateMutability": "view",
    "type": "function"
  },
  {
    "inputs": [],
    "name": "minStaking",
    "outputs": [
      {
        "internalType": "uint256",
        "name": "",
        "type": "uint256"
      }
    ],
    "stateMutability": "view",
    "type": "function"
  },
  {
    "inputs": [],
    "name": "oracle",
    "outputs": [
      {
        "internalType": "address",
        "name": "",
        "type": "address"
      }
    ],
    "stateMutability": "view",
    "type": "function"
  },
  {
    "inputs": [],
    "name": "orders",
    "outputs": [
      {
        "internalType": "bytes32[]",
        "name": "",
        "type": "bytes32[]"
      }
    ],
    "stateMutability": "view",
    "type": "function"
  },
  {
    "inputs": [
      {
        "internalType": "bytes32",
        "name": "",
        "type": "bytes32"
      }
    ],
    "name": "ordersIndex",
    "outputs": [
      {
        "internalType": "uint256",
        "name": "",
        "type": "uint256"
      }
    ],
    "stateMutability": "view",
    "type": "function"
  },
  {
    "inputs": [],
    "name": "owner",
    "outputs": [
      {
        "internalType": "address",
        "name": "",
        "type": "address"
      }
    ],
    "stateMutability": "view",
    "type": "function"
  },
  {
    "inputs": [],
    "name": "pause",
    "outputs": [],
    "stateMutability": "nonpayable",
    "type": "function"
  },
  {
    "inputs": [],
    "name": "paused",
    "outputs": [
      {
        "internalType": "bool",
        "name": "",
        "type": "bool"
      }
    ],
    "stateMutability": "view",
    "type": "function"
  },
  {
    "inputs": [],
    "name": "payee",
    "outputs": [
      {
        "internalType": "address",
        "name": "",
        "type": "address"
      }
    ],
    "stateMutability": "view",
    "type": "function"
  },
  {
    "inputs": [
      {
        "internalType": "bytes",
        "name": "performData",
        "type": "bytes"
      }
    ],
    "name": "performUpkeep",
    "outputs": [],
    "stateMutability": "nonpayable",
    "type": "function"
  },
  {
    "inputs": [],
    "name": "poolFee",
    "outputs": [
      {
        "internalType": "uint24",
        "name": "",
        "type": "uint24"
      }
    ],
    "stateMutability": "view",
    "type": "function"
  },
  {
    "inputs": [],
    "name": "renounceOwnership",
    "outputs": [],
    "stateMutability": "nonpayable",
    "type": "function"
  },
  {
    "inputs": [
      {
        "internalType": "address",
        "name": "",
        "type": "address"
      }
    ],
    "name": "savingsRate",
    "outputs": [
      {
        "internalType": "uint256",
        "name": "",
        "type": "uint256"
      }
    ],
    "stateMutability": "view",
    "type": "function"
  },
  {
    "inputs": [
      {
        "internalType": "address",
        "name": "newBuilder",
        "type": "address"
      }
    ],
    "name": "setBuilder",
    "outputs": [],
    "stateMutability": "nonpayable",
    "type": "function"
  },
  {
    "inputs": [
      {
        "internalType": "uint256",
        "name": "newAmount",
        "type": "uint256"
      }
    ],
    "name": "setMinStaking",
    "outputs": [],
    "stateMutability": "nonpayable",
    "type": "function"
  },
  {
    "inputs": [
      {
        "internalType": "address",
        "name": "newOracle",
        "type": "address"
      }
    ],
    "name": "setOracle",
    "outputs": [],
    "stateMutability": "nonpayable",
    "type": "function"
  },
  {
    "inputs": [
      {
        "internalType": "address",
        "name": "newPayee",
        "type": "address"
      }
    ],
    "name": "setPayee",
    "outputs": [],
    "stateMutability": "nonpayable",
    "type": "function"
  },
  {
    "inputs": [
      {
        "internalType": "uint24",
        "name": "newFee",
        "type": "uint24"
      }
    ],
    "name": "setPoolFee",
    "outputs": [],
    "stateMutability": "nonpayable",
    "type": "function"
  },
  {
    "inputs": [
      {
        "internalType": "address",
        "name": "token",
        "type": "address"
      },
      {
        "internalType": "uint256",
        "name": "rate",
        "type": "uint256"
      }
    ],
    "name": "setSavingsRate",
    "outputs": [],
    "stateMutability": "nonpayable",
    "type": "function"
  },
  {
    "inputs": [
      {
        "internalType": "address",
        "name": "newTech",
        "type": "address"
      }
    ],
    "name": "setTech",
    "outputs": [],
    "stateMutability": "nonpayable",
    "type": "function"
  },
  {
    "inputs": [
      {
        "internalType": "address",
        "name": "newTreasury",
        "type": "address"
      }
    ],
    "name": "setTreasury",
    "outputs": [],
    "stateMutability": "nonpayable",
    "type": "function"
  },
  {
    "inputs": [],
    "name": "stakingReward",
    "outputs": [
      {
        "internalType": "address",
        "name": "",
        "type": "address"
      }
    ],
    "stateMutability": "view",
    "type": "function"
  },
  {
    "inputs": [],
    "name": "tech",
    "outputs": [
      {
        "internalType": "address",
        "name": "",
        "type": "address"
      }
    ],
    "stateMutability": "view",
    "type": "function"
  },
  {
    "inputs": [
      {
        "internalType": "address",
        "name": "",
        "type": "address"
      }
    ],
    "name": "totalSavings",
    "outputs": [
      {
        "internalType": "uint256",
        "name": "",
        "type": "uint256"
      }
    ],
    "stateMutability": "view",
    "type": "function"
  },
  {
    "inputs": [
      {
        "internalType": "address",
        "name": "newOwner",
        "type": "address"
      }
    ],
    "name": "transferOwnership",
    "outputs": [],
    "stateMutability": "nonpayable",
    "type": "function"
  },
  {
    "inputs": [],
    "name": "treasury",
    "outputs": [
      {
        "internalType": "address",
        "name": "",
        "type": "address"
      }
    ],
    "stateMutability": "view",
    "type": "function"
  },
  {
    "inputs": [],
    "name": "unpause",
    "outputs": [],
    "stateMutability": "nonpayable",
    "type": "function"
  },
  {
    "inputs": [
      {
        "internalType": "bytes32",
        "name": "orderHash",
        "type": "bytes32"
      }
    ],
    "name": "updateUserPeriodFinish",
    "outputs": [],
    "stateMutability": "nonpayable",
    "type": "function"
  },
  {
    "inputs": [
      {
        "internalType": "bytes32",
        "name": "",
        "type": "bytes32"
      }
    ],
    "name": "users",
    "outputs": [
      {
        "internalType": "address",
        "name": "account",
        "type": "address"
      },
      {
        "internalType": "address",
        "name": "token",
        "type": "address"
      },
      {
        "internalType": "uint256",
        "name": "balance",
        "type": "uint256"
      },
      {
        "internalType": "uint256",
        "name": "value",
        "type": "uint256"
      },
      {
        "internalType": "uint256",
        "name": "interest",
        "type": "uint256"
      },
      {
        "internalType": "uint256",
        "name": "interestPerSavingsRateReleased",
        "type": "uint256"
      },
      {
        "internalType": "uint256",
        "name": "periodFinish",
        "type": "uint256"
      },
      {
        "internalType": "uint256",
        "name": "lastUpdateTime",
        "type": "uint256"
      }
    ],
    "stateMutability": "view",
    "type": "function"
  },
  {
    "inputs": [
      {
        "internalType": "bytes32",
        "name": "orderHash",
        "type": "bytes32"
      }
    ],
    "name": "withdraw",
    "outputs": [],
    "stateMutability": "nonpayable",
    "type": "function"
  }
]
